osny_imagem_processing/__init__.py
osny_imagem_processing/processing/__init__.py
osny_imagem_processing/processing/combination.py
osny_imagem_processing/processing/transformation.py
osny_imagem_processing/utils/__init__.py
osny_imagem_processing/utils/io.py
osny_imagem_processing/utils/plot.py
osny_processing_imagem/__init__.py
osny_processing_imagem/processing/__init__.py
osny_processing_imagem/processing/combination.py
osny_processing_imagem/processing/transformation.py
osny_processing_imagem/utils/__init__.py
osny_processing_imagem/utils/io.py
osny_processing_imagem/utils/plot.py
processamento_imagens/__init__.py
processamento_imagens/processing/__init__.py
processamento_imagens/processing/combination.py
processamento_imagens/processing/transformation.py
processamento_imagens/utils/__init__.py
processamento_imagens/utils/io.py
processamento_imagens/utils/plot.py
processamento_imagens_com_python/__init__.py
processamento_imagens_com_python/processing/__init__.py
processamento_imagens_com_python/processing/combination.py
processamento_imagens_com_python/processing/transformation.py
processamento_imagens_com_python/utils/__init__.py
processamento_imagens_com_python/utils/io.py
processamento_imagens_com_python/utils/plot.py
processamento_imagens_osny/__init__.py
processamento_imagens_osny/processing/__init__.py
processamento_imagens_osny/processing/combination.py
processamento_imagens_osny/processing/transformation.py
processamento_imagens_osny/utils/__init__.py
processamento_imagens_osny/utils/io.py
processamento_imagens_osny/utils/plot.py
osny_processing_imagem-0.0.1.dist-info/METADATA
osny_processing_imagem-0.0.1.dist-info/WHEEL
osny_processing_imagem-0.0.1.dist-info/top_level.txt
osny_processing_imagem-0.0.1.dist-info/RECORD
