Metadata-Version: 2.4
Name: osny_processing_imagem
Version: 0.0.1
Summary: Processamento de imagens com Python
Home-page: https://github.com/OsnyNeto/Programas_Python/tree/main/osny_imagem_processing
Author: Osny Neto
Author-email: osnynt@gmail.com
Requires-Python: >=3.8
Dynamic: author
Dynamic: author-email
Dynamic: description
Dynamic: description-content-type
Dynamic: home-page
Dynamic: requires-python
Dynamic: summary
